fasteners/__init__.py
fasteners/_utils.py
fasteners/lock.py
fasteners/process_lock.py
fasteners/version.py
fasteners/pywin32/__init__.py
fasteners/pywin32/pywintypes.py
fasteners/pywin32/win32con.py
fasteners/pywin32/win32file.py
fasteners-0.17.2.dist-info/LICENSE
fasteners-0.17.2.dist-info/METADATA
fasteners-0.17.2.dist-info/WHEEL
fasteners-0.17.2.dist-info/top_level.txt
fasteners-0.17.2.dist-info/RECORD
